{
  "meta": {
    "child": "弟弟",
    "title": "一下·身体与动物",
    "grade": 1
  },
  "items": [
    { "word": "head", "meaning": "头", "ipa": "/hed/", "type": "word", "example": "I have a big head.", "exampleMeaning": "我有一个大脑袋。" },
    { "word": "face", "meaning": "脸", "ipa": "/feɪs/", "type": "word", "example": "Wash your face.", "exampleMeaning": "洗洗脸。" },
    { "word": "nose", "meaning": "鼻子", "ipa": "/nəʊz/", "type": "word", "example": "My nose is small.", "exampleMeaning": "我的鼻子很小。" },
    { "word": "eye", "meaning": "眼睛", "ipa": "/aɪ/", "type": "word", "example": "I have two eyes.", "exampleMeaning": "我有两只眼睛。" },
    { "word": "ear", "meaning": "耳朵", "ipa": "/ɪə(r)/", "type": "word", "example": "The rabbit has long ears.", "exampleMeaning": "兔子有长耳朵。" },
    { "word": "mouth", "meaning": "嘴", "ipa": "/maʊθ/", "type": "word", "example": "Open your mouth.", "exampleMeaning": "张开嘴。" },
    { "word": "hand", "meaning": "手", "ipa": "/hænd/", "type": "word", "example": "I have two hands.", "exampleMeaning": "我有两只手。" },
    { "word": "arm", "meaning": "胳膊", "ipa": "/ɑːm/", "type": "word", "example": "My arm is strong.", "exampleMeaning": "我的胳膊很强壮。" },
    { "word": "leg", "meaning": "腿", "ipa": "/leɡ/", "type": "word", "example": "I have two legs.", "exampleMeaning": "我有两条腿。" },
    { "word": "foot", "meaning": "脚", "ipa": "/fʊt/", "type": "word", "example": "My foot is big.", "exampleMeaning": "我的脚很大。" },
    { "word": "feet", "meaning": "脚（复数）", "ipa": "/fiːt/", "type": "word", "example": "I have two feet.", "exampleMeaning": "我有两只脚。" },
    { "word": "body", "meaning": "身体", "ipa": "/ˈbɒdi/", "type": "word", "example": "My body is strong.", "exampleMeaning": "我的身体很强壮。" },
    { "word": "touch", "meaning": "触摸", "ipa": "/tʌtʃ/", "type": "word", "example": "Touch your nose.", "exampleMeaning": "摸摸你的鼻子。" },
    { "word": "baby", "meaning": "婴儿", "ipa": "/ˈbeɪbi/", "type": "word", "example": "The baby is cute.", "exampleMeaning": "这个婴儿很可爱。" },
    { "word": "these", "meaning": "这些", "ipa": "/ðiːz/", "type": "word", "example": "These are my toys.", "exampleMeaning": "这些是我的玩具。" },
    { "word": "they", "meaning": "它们/他们/她们", "ipa": "/ðeɪ/", "type": "word", "example": "They are on the farm.", "exampleMeaning": "它们在农场上。" },
    { "word": "they're", "meaning": "它们是", "ipa": "/ðeə(r)/", "type": "word", "example": "They're cows.", "exampleMeaning": "它们是奶牛。" },
    { "word": "cow", "meaning": "奶牛", "ipa": "/kaʊ/", "type": "word", "example": "The cow is big.", "exampleMeaning": "这头奶牛很大。" },
    { "word": "pig", "meaning": "猪", "ipa": "/pɪɡ/", "type": "word", "example": "The pig is fat.", "exampleMeaning": "这头猪很胖。" },
    { "word": "duck", "meaning": "鸭子", "ipa": "/dʌk/", "type": "word", "example": "The duck can swim.", "exampleMeaning": "鸭子会游泳。" },
    { "word": "chicken", "meaning": "鸡", "ipa": "/ˈtʃɪkɪn/", "type": "word", "example": "The chicken is small.", "exampleMeaning": "这只鸡很小。" },
    { "word": "farm", "meaning": "农场", "ipa": "/fɑːm/", "type": "word", "example": "I live on a farm.", "exampleMeaning": "我住在农场。" },
    { "word": "fat", "meaning": "胖的", "ipa": "/fæt/", "type": "word", "example": "The pig is fat.", "exampleMeaning": "这头猪很胖。" },
    { "word": "big", "meaning": "大的", "ipa": "/bɪɡ/", "type": "word", "example": "The cow is big.", "exampleMeaning": "这头奶牛很大。" },
    { "word": "little", "meaning": "小的", "ipa": "/ˈlɪtl/", "type": "word", "example": "The duck is little.", "exampleMeaning": "这只鸭子很小。" },
    { "word": "thin", "meaning": "瘦的", "ipa": "/θɪn/", "type": "word", "example": "The cat is thin.", "exampleMeaning": "这只猫很瘦。" },
    { "word": "egg", "meaning": "鸡蛋", "ipa": "/eɡ/", "type": "word", "example": "I like eggs.", "exampleMeaning": "我喜欢鸡蛋。" },
    { "word": "very", "meaning": "非常", "ipa": "/ˈveri/", "type": "word", "example": "It is very big.", "exampleMeaning": "它非常大。" },
    { "word": "snake", "meaning": "蛇", "ipa": "/sneɪk/", "type": "word", "example": "The snake is long.", "exampleMeaning": "这条蛇很长。" },
    { "word": "giraffe", "meaning": "长颈鹿", "ipa": "/dʒəˈrɑːf/", "type": "word", "example": "The giraffe is tall.", "exampleMeaning": "长颈鹿很高。" },
    { "word": "elephant", "meaning": "大象", "ipa": "/ˈelɪfənt/", "type": "word", "example": "The elephant is big.", "exampleMeaning": "大象很大。" },
    { "word": "tiger", "meaning": "老虎", "ipa": "/ˈtaɪɡə(r)/", "type": "word", "example": "The tiger is strong.", "exampleMeaning": "老虎很强壮。" },
    { "word": "horse", "meaning": "马", "ipa": "/hɔːs/", "type": "word", "example": "The horse can run.", "exampleMeaning": "马会跑。" },
    { "word": "zoo", "meaning": "动物园", "ipa": "/zuː/", "type": "word", "example": "Let's go to the zoo.", "exampleMeaning": "我们去动物园吧。" },
    { "word": "tall", "meaning": "高的", "ipa": "/tɔːl/", "type": "word", "example": "The tree is tall.", "exampleMeaning": "这棵树很高。" },
    { "word": "short", "meaning": "矮的；短的", "ipa": "/ʃɔːt/", "type": "word", "example": "The dog is short.", "exampleMeaning": "这只狗很矮。" },
    { "word": "long", "meaning": "长的", "ipa": "/lɒŋ/", "type": "word", "example": "The snake is long.", "exampleMeaning": "这条蛇很长。" },
    { "word": "small", "meaning": "小的", "ipa": "/smɔːl/", "type": "word", "example": "The egg is small.", "exampleMeaning": "这个鸡蛋很小。" },
    { "word": "strong", "meaning": "强壮的", "ipa": "/strɒŋ/", "type": "word", "example": "The tiger is strong.", "exampleMeaning": "老虎很强壮。" },
    { "word": "cute", "meaning": "可爱的", "ipa": "/kjuːt/", "type": "word", "example": "The baby is cute.", "exampleMeaning": "这个婴儿很可爱。" },
    { "word": "go", "meaning": "去", "ipa": "/ɡəʊ/", "type": "word", "example": "Let's go to the zoo.", "exampleMeaning": "我们去动物园吧。" },
    { "word": "aren't", "meaning": "不是", "ipa": "/ɑːnt/", "type": "word", "example": "They aren't big.", "exampleMeaning": "它们不大。" }
  ]
}
